{
    "Statement": [
        {
            "Action": [
                "s3:ListBucket",
                "s3:GetObjectTagging",
                "s3:PutObjectTagging",
                "s3:PutObject",
                "s3:PutObjectAcl",
                "s3:GetObject",
                "s3:GetObjectAcl",
                "s3:DeleteObject"
            ],
            "Effect": "Allow",
            "Principal": "*",
            "Resource": [
                "arn:aws:s3:::hdva-zip-bucket/*.zip"
            ]
        }
    ],
    "Version": "2012-10-17"
}